multisensor_pipeline/__init__.py
multisensor_pipeline/dataframe/__init__.py
multisensor_pipeline/dataframe/dataframe.py
multisensor_pipeline/modules/__init__.py
multisensor_pipeline/modules/keyboard.py
multisensor_pipeline/modules/mouse.py
multisensor_pipeline/modules/multiprocess.py
multisensor_pipeline/modules/network.py
multisensor_pipeline/modules/npy.py
multisensor_pipeline/modules/audio/__init__.py
multisensor_pipeline/modules/audio/file.py
multisensor_pipeline/modules/audio/microphone.py
multisensor_pipeline/modules/base/__init__.py
multisensor_pipeline/modules/base/base.py
multisensor_pipeline/modules/base/profiling.py
multisensor_pipeline/modules/base/sampling.py
multisensor_pipeline/modules/image/__init__.py
multisensor_pipeline/modules/image/pillow.py
multisensor_pipeline/modules/image/utils.py
multisensor_pipeline/modules/persistence/__init__.py
multisensor_pipeline/modules/persistence/dataset.py
multisensor_pipeline/modules/persistence/recording.py
multisensor_pipeline/modules/persistence/replay.py
multisensor_pipeline/modules/signal/__init__.py
multisensor_pipeline/modules/signal/filtering.py
multisensor_pipeline/modules/signal/one_euro_filter.py
multisensor_pipeline/modules/signal/sampling.py
multisensor_pipeline/modules/video/__init__.py
multisensor_pipeline/modules/video/video.py
multisensor_pipeline/modules/video/webcam.py
multisensor_pipeline/pipeline/__init__.py
multisensor_pipeline/pipeline/base.py
multisensor_pipeline/pipeline/graph.py
multisensor_pipeline/tests/__init__.py
multisensor_pipeline/tests/test_audio.py
multisensor_pipeline/tests/test_basic.py
multisensor_pipeline/tests/test_image.py
multisensor_pipeline/tests/test_input.py
multisensor_pipeline/tests/test_multiprocessing.py
multisensor_pipeline/tests/test_network.py
multisensor_pipeline/tests/test_persistence.py
multisensor_pipeline/tests/test_profiling.py
multisensor_pipeline/tests/test_sample_generation.py
multisensor_pipeline/tests/test_signal.py
multisensor_pipeline-2.1.0.dist-info/LICENSE.txt
multisensor_pipeline-2.1.0.dist-info/METADATA
multisensor_pipeline-2.1.0.dist-info/WHEEL
multisensor_pipeline-2.1.0.dist-info/top_level.txt
multisensor_pipeline-2.1.0.dist-info/RECORD
